{
    "data": {
        "doctors": [
            {
                "description": "Провожу онлайн консультации взрослого и детского населения на сайте. А также веду амбулаторно-поликлинический прием пациентов с острыми и хроническими офтальмологическими заболеваниями переднего и заднего отрезков глаз.",
                "slot_date": {
                    "2025-01-23T00:00:00Z": [
                        "17:00",
                        "18:00",
                        "18:30",
                        "18:50",
                        "19:00",
                        "19:30",
                        "19:00",
                        "17:00"
                    ],
                    "2025-01-25T00:00:00Z": [
                        "12:00",
                        "13:00",
                        "14:30",
                        "14:50",
                        "19:00",
                        "19:30"
                    ],
                    "2025-01-26T00:00:00Z": [
                        "17:30",
                        "18:00",
                        "18:30",
                        "18:50",
                        "19:00",
                        "17:00",
                        "17:00"
                    ],
                    "2025-01-30T00:00:00Z": [
                        "13:00",
                        "14:30",
                        "18:30",
                        "18:30",
                        "19:00",
                        "19:30",
                        "17:00",
                        "17:00"
                    ],
                    "2025-02-03T00:00:00Z": ["13:00", "14:00", "18:30", "18:50"]
                },
                "doctor": {
                    "doctor_id": 1,
                    "fullname": "Abdullin Ramzil Razilevich",
                    "phone_number": "79393376666",
                    "image": "https://gbuzrkib.ru/upload/iblock/2ec/lqao211pgxbf6sa5glzfyk1vd9bt5qf7.jpg",
                    "experience": 10
                },
                "qualification": [
                    {
                        "education_name": "КГМУ",
                        "year": 2003
                    },
                    {
                        "education_name": "Кфу, медицинаский факутльтет",
                        "year": 2009
                    }
                ],
                "reviews": [
                    {
                        "phone": "+1234567890",
                        "date": "Wed, 10 Jan 2024 14:30:00 GMT",
                        "description": "Отличный врач, очень доволен!"
                    },
                    {
                        "phone": "+7934567890",
                        "date": "Wed, 10 Jan 2024 14:30:00 GMT",
                        "description": "С мнением врача согласен, хороший специалист, пишет не по скрипту а видно что смотрит"
                    },
                    {
                        "phone": "+7934567890",
                        "date": "Wed, 10 Jan 2024 14:30:00 GMT",
                        "description": "Очень помог мне разобраться в моей проблеме и рассказал пути решения. Терпеливо ответил на все мои вопросы и был очень доброжелательным. Спасибо!"
                    }
                ],
                "specialties": [
                    {
                        "speciality_id": 1,
                        "speciality_name": "Терапевт"
                    },
                    {
                        "speciality_id": 2,
                        "speciality_name": "Хирург"
                    }
                ],
                "house_call": true
            },
            {
                "description": "В настоящее время работаю в частной клинике. Веду приём пациентов с миомой, эндометриозом, бесплодием, нарушениями менструального цикла, климактерическими нарушениями,воспалительными заболеваниями, патологией шейки матки. Занимаюсь вопросами планирования и ведения беременности. Все назначения обследования и лечения в рамках доказательной медицины.",
                "slot_date": {
                    "2025-01-13T00:00:00Z": [
                        "17:00",
                        "18:00",
                        "18:30",
                        "18:50",
                        "19:00",
                        "19:30",
                        "19:00",
                        "17:00"
                    ],
                    "2025-01-14T00:00:00Z": [
                        "11:00",
                        "13:00",
                        "14:30",
                        "14:50",
                        "19:00",
                        "19:30"
                    ],
                    "2025-01-15T00:00:00Z": [
                        "17:30",
                        "18:00",
                        "18:30",
                        "18:50",
                        "19:00",
                        "17:00",
                        "17:00"
                    ],
                    "2025-01-16T00:00:00Z": [
                        "13:00",
                        "14:30",
                        "18:30",
                        "18:30",
                        "19:00",
                        "19:30",
                        "17:00",
                        "17:00"
                    ],
                    "2025-01-17T00:00:00Z": [
                        "13:00",
                        "14:00",
                        "18:30",
                        "18:50"
                    ],
                    "2025-01-19T00:00:00Z": [
                        "13:00",
                        "14:00",
                        "18:30",
                        "18:50"
                    ],
                    "2025-01-20T00:00:00Z": [
                        "13:00",
                        "14:00",
                        "18:30",
                        "18:50"
                    ],
                    "2025-02-03T00:00:00Z": ["13:00", "14:00", "18:30", "18:50"]
                },
                "doctor": {
                    "doctor_id": 2,
                    "fullname": "Лавров Никанор Васильевич",
                    "phone_number": "79993376777",
                    "image": "https://i.pinimg.com/originals/95/36/56/953656e464dcbe4fe7c142e16dfd9303.jpg",
                    "experience": 11
                },
                "qualification": [
                    {
                        "education_name": "КГМУ",
                        "year": 2003
                    },
                    {
                        "education_name": "Кфу, медицинаский факутльтет",
                        "year": 2009
                    }
                ],
                "reviews": [
                    {
                        "phone": "+1234567890",
                        "date": "Wed, 10 Jan 2024 14:30:00 GMT",
                        "description": "Отличный врач, очень доволен!"
                    },
                    {
                        "phone": "+7934567890",
                        "date": "Wed, 10 Jan 2024 14:30:00 GMT",
                        "description": "С мнением врача согласен, хороший специалист, пишет не по скрипту а видно что смотрит"
                    },
                    {
                        "phone": "+7934567890",
                        "date": "Wed, 10 Jan 2024 14:30:00 GMT",
                        "description": "Очень помог мне разобраться в моей проблеме и рассказал пути решения. Терпеливо ответил на все мои вопросы и был очень доброжелательным. Спасибо!"
                    }
                ],
                "specialties": [
                    {
                        "speciality_id": 1,
                        "speciality_name": "Терапевт"
                    }
                ],
                "house_call": true
            },
            {
                "description": "Использую в работе доказательную медицину, но народной не пренебрегаю. Дорогую процедуру могу рекомендовать, если к ней есть показания. На поводу у пациентов не иду и иногда даю совет сменить врача, если пациент игнорирует рекомендации.",
                "slot_date": {
                    "2025-01-13T00:00:00Z": [
                        "17:00",
                        "18:00",
                        "18:30",
                        "18:50",
                        "19:00",
                        "19:30",
                        "19:00",
                        "17:00"
                    ],
                    "2025-01-14T00:00:00Z": [
                        "11:00",
                        "13:00",
                        "14:30",
                        "14:50",
                        "19:00",
                        "19:30"
                    ],
                    "2025-01-15T00:00:00Z": [
                        "17:30",
                        "18:00",
                        "18:30",
                        "18:50",
                        "19:00",
                        "17:00",
                        "17:00"
                    ],
                    "2025-01-16T00:00:00Z": [
                        "13:00",
                        "14:30",
                        "18:30",
                        "18:30",
                        "19:00",
                        "19:30",
                        "17:00",
                        "17:00"
                    ],
                    "2025-01-17T00:00:00Z": [
                        "13:00",
                        "14:00",
                        "18:30",
                        "18:50"
                    ],
                    "2025-01-18T00:00:00Z": [
                        "13:00",
                        "14:00",
                        "18:30",
                        "18:50"
                    ],
                    "2025-01-19T00:00:00Z": [
                        "13:00",
                        "14:00",
                        "18:30",
                        "18:50"
                    ],
                    "2025-01-20T00:00:00Z": [
                        "13:00",
                        "14:00",
                        "18:30",
                        "18:50"
                    ],
                    "2025-01-21T00:00:00Z": [
                        "13:00",
                        "14:00",
                        "18:30",
                        "18:50"
                    ],
                    "2025-01-22T00:00:00Z": [
                        "13:00",
                        "14:00",
                        "18:30",
                        "18:50"
                    ],
                    "2025-01-23T00:00:00Z": [
                        "13:00",
                        "14:00",
                        "18:30",
                        "18:50"
                    ],
                    "2025-01-24T00:00:00Z": [
                        "13:00",
                        "14:00",
                        "18:30",
                        "18:50"
                    ],
                    "2025-01-27T00:00:00Z": [
                        "13:00",
                        "14:00",
                        "18:30",
                        "18:50"
                    ],
                    "2025-01-28T00:00:00Z": [
                        "13:00",
                        "14:00",
                        "18:30",
                        "18:50"
                    ],
                    "2025-01-29T00:00:00Z": [
                        "13:00",
                        "14:00",
                        "18:30",
                        "18:50"
                    ],
                    "2025-01-30T00:00:00Z": [
                        "13:00",
                        "14:00",
                        "18:30",
                        "18:50"
                    ],
                    "2025-01-31T00:00:00Z": [
                        "13:00",
                        "14:00",
                        "18:30",
                        "18:50"
                    ],
                    "2025-02-02T00:00:00Z": [
                        "13:00",
                        "14:00",
                        "18:30",
                        "18:50"
                    ],
                    "2025-02-10T00:00:00Z": ["13:00", "14:00", "18:30", "18:50"]
                },
                "doctor": {
                    "doctor_id": 3,
                    "fullname": "Алексеева Виктория Сергеевна",
                    "phone_number": "89493376777",
                    "image": "https://i.pinimg.com/originals/1b/52/fd/1b52fd81c2282b432b85dc6a8a01f13d.jpg",
                    "experience": 6
                },
                "qualification": [
                    {
                        "education_name": "КГМУ",
                        "year": 2003
                    },
                    {
                        "education_name": "Кфу, медицинаский факутльтет",
                        "year": 2009
                    }
                ],
                "reviews": [
                    {
                        "phone": "+1234567890",
                        "date": "Wed, 10 Jan 2024 14:30:00 GMT",
                        "description": "Отличный врач, очень доволен!"
                    },
                    {
                        "phone": "+7934567890",
                        "date": "Wed, 10 Jan 2024 14:30:00 GMT",
                        "description": "С мнением врача согласен, хороший специалист, пишет не по скрипту а видно что смотрит"
                    },
                    {
                        "phone": "+7934567890",
                        "date": "Wed, 10 Jan 2024 14:30:00 GMT",
                        "description": "Очень помог мне разобраться в моей проблеме и рассказал пути решения. Терпеливо ответил на все мои вопросы и был очень доброжелательным. Спасибо!"
                    }
                ],
                "specialties": [
                    {
                        "speciality_id": 3,
                        "speciality_name": "Кардиолог"
                    }
                ],
                "house_call": false
            },
            {
                "description": "Занимаюсь профилактикой и лечением сердечно-сосудистых заболеваний. Использую методы доказательной медицины. Сотрудничаю со смежными специалистами для решения сложных лечебно-диагностических вопросов.",
                "slot_date": {
                    "2025-01-13T00:00:00Z": [
                        "17:00",
                        "18:00",
                        "18:30",
                        "18:50",
                        "19:00",
                        "19:30",
                        "19:00",
                        "17:00"
                    ],
                    "2025-01-16T00:00:00Z": [
                        "11:00",
                        "13:00",
                        "14:30",
                        "14:50",
                        "19:00",
                        "19:30"
                    ],
                    "2025-01-23T00:00:00Z": [
                        "17:30",
                        "18:00",
                        "18:30",
                        "18:50",
                        "19:00",
                        "17:00",
                        "17:00"
                    ],
                    "2025-01-29T00:00:00Z": [
                        "13:00",
                        "14:30",
                        "18:30",
                        "18:30",
                        "19:00",
                        "19:30",
                        "17:00",
                        "17:00"
                    ],
                    "2025-02-10T00:00:00Z": [
                        "13:00",
                        "14:00",
                        "18:30",
                        "18:50"
                    ],
                    "2025-02-11T00:00:00Z": [
                        "13:00",
                        "14:00",
                        "18:30",
                        "18:50"
                    ],
                    "2025-02-12T00:00:00Z": ["13:00", "14:00", "18:30", "18:50"]
                },
                "doctor": {
                    "doctor_id": 4,
                    "fullname": "Кулиш Вера Анатольевна",
                    "phone_number": "89113376777",
                    "image": "https://i.pinimg.com/originals/27/95/70/279570b530f74c37ef61bd356cd63f2c.jpg",
                    "experience": 14
                },
                "qualification": [
                    {
                        "education_name": "КГМУ",
                        "year": 2003
                    },
                    {
                        "education_name": "Кфу, медицинаский факутльтет",
                        "year": 2009
                    }
                ],
                "reviews": [
                    {
                        "phone": "+1234567890",
                        "date": "Wed, 10 Jan 2024 14:30:00 GMT",
                        "description": "Отличный врач, очень доволен!"
                    },
                    {
                        "phone": "+7934567890",
                        "date": "Wed, 10 Jan 2024 14:30:00 GMT",
                        "description": "С мнением врача согласен, хороший специалист, пишет не по скрипту а видно что смотрит"
                    },
                    {
                        "phone": "+7934567890",
                        "date": "Wed, 10 Jan 2024 14:30:00 GMT",
                        "description": "Очень помог мне разобраться в моей проблеме и рассказал пути решения. Терпеливо ответил на все мои вопросы и был очень доброжелательным. Спасибо!"
                    }
                ],
                "specialties": [
                    {
                        "speciality_id": 3,
                        "speciality_name": "Кардиолог"
                    }
                ],
                "house_call": true
            },
            {
                "description": "Занимаюсь профилактикой и лечением сердечно-сосудистых заболеваний. Использую методы доказательной медицины. Сотрудничаю со смежными специалистами для решения сложных лечебно-диагностических вопросов.",

                "slot_date": {
                    "2025-01-13T00:00:00Z": [
                        "17:00",
                        "18:00",
                        "18:30",
                        "18:50",
                        "19:00",
                        "19:30",
                        "19:00",
                        "17:00"
                    ],
                    "2025-02-01T00:00:00Z": [
                        "11:00",
                        "13:00",
                        "14:30",
                        "14:50",
                        "19:00",
                        "19:30"
                    ],
                    "2025-02-03T00:00:00Z": [
                        "17:30",
                        "18:00",
                        "18:30",
                        "18:50",
                        "19:00",
                        "17:00",
                        "17:00"
                    ],
                    "2025-02-10T00:00:00Z": [
                        "13:00",
                        "14:30",
                        "18:30",
                        "18:30",
                        "19:00",
                        "19:30",
                        "17:00",
                        "17:00"
                    ],
                    "2025-02-11T00:00:00Z": [
                        "13:00",
                        "14:00",
                        "18:30",
                        "18:50"
                    ],
                    "2025-02-12T00:00:00Z": [
                        "13:00",
                        "14:00",
                        "18:30",
                        "18:50"
                    ],
                    "2025-02-13T00:00:00Z": ["13:00", "14:00", "18:30", "18:50"]
                },
                "doctor": {
                    "doctor_id": 5,
                    "fullname": "Калинкина Алена Олеговна",
                    "phone_number": "79993376777",
                    "image": "https://i.pinimg.com/originals/95/36/56/953656e464dcbe4fe7c142e16dfd9303.jpg",
                    "experience": 3
                },
                "qualification": [
                    {
                        "education_name": "КГМУ",
                        "year": 2003
                    },
                    {
                        "education_name": "Кфу, медицинаский факутльтет",
                        "year": 2009
                    }
                ],
                "reviews": [
                    {
                        "phone": "+1234567890",
                        "date": "Wed, 10 Jan 2024 14:30:00 GMT",
                        "description": "Отличный врач, очень доволен!"
                    },
                    {
                        "phone": "+7934567890",
                        "date": "Wed, 10 Jan 2024 14:30:00 GMT",
                        "description": "С мнением врача согласен, хороший специалист, пишет не по скрипту а видно что смотрит"
                    },
                    {
                        "phone": "+7934567890",
                        "date": "Wed, 10 Jan 2024 14:30:00 GMT",
                        "description": "Очень помог мне разобраться в моей проблеме и рассказал пути решения. Терпеливо ответил на все мои вопросы и был очень доброжелательным. Спасибо!"
                    }
                ],
                "specialties": [
                    {
                        "speciality_id": 1,
                        "speciality_name": "Терапевт"
                    }
                ],
                "house_call": false
            }
        ],
        "categories": ["Терапевт", "Хирург", "Кардиолог", "Педиатр"]
    },
    "error_message": null,
    "success": 1
}
